evalmyai/__init__.py
evalmyai/_evalmyai.py
evalmyai/_utils.py
evalmyai/_validators.py
evalmyai-0.1.0a12.dist-info/licenses/LICENSE
evalmyai-0.1.0a12.dist-info/METADATA
evalmyai-0.1.0a12.dist-info/WHEEL
evalmyai-0.1.0a12.dist-info/top_level.txt
evalmyai-0.1.0a12.dist-info/RECORD
