Metadata-Version: 2.4
Name: evalmyai
Version: 0.1.0a12
Summary: EVALMY.AI Python library
License:                                  Apache License
Classifier: Intended Audience :: Developers
Classifier: Intended Audience :: Science/Research
Classifier: Intended Audience :: Education
Classifier: Operating System :: MacOS :: MacOS X
Classifier: Operating System :: Microsoft :: Windows
Classifier: Operating System :: POSIX
Classifier: Programming Language :: Python :: 3
License-File: LICENSE
Requires-Dist: requests
Requires-Dist: pandas
Dynamic: license-file
